mssql_mcp/__init__.py
mssql_mcp/app.py
mssql_mcp/config.py
mssql_mcp/connection.py
mssql_mcp/server.py
mssql_mcp/auth/__init__.py
mssql_mcp/auth/callback.py
mssql_mcp/auth/provider.py
mssql_mcp/auth/storage.py
mssql_mcp/auth/idp/__init__.py
mssql_mcp/auth/idp/auth0.py
mssql_mcp/auth/idp/base.py
mssql_mcp/auth/idp/duo.py
mssql_mcp/auth/idp/oidc.py
mssql_mcp/resources/__init__.py
mssql_mcp/resources/examples.py
mssql_mcp/resources/knowledge.py
mssql_mcp/resources/syntax_help.py
mssql_mcp/tools/__init__.py
mssql_mcp/tools/crud.py
mssql_mcp/tools/databases.py
mssql_mcp/tools/export.py
mssql_mcp/tools/knowledge.py
mssql_mcp/tools/query.py
mssql_mcp/tools/stored_procs.py
mssql_mcp/tools/tables.py
mssql_mcp/tools/transaction.py
mssql_mcp/utils/__init__.py
mssql_mcp/utils/audit.py
mssql_mcp/utils/knowledge.py
mssql_mcp/utils/safety.py
mssql_mcp/utils/watchdog.py
pymssql_mcp-0.4.2.dist-info/METADATA
pymssql_mcp-0.4.2.dist-info/WHEEL
pymssql_mcp-0.4.2.dist-info/entry_points.txt
pymssql_mcp-0.4.2.dist-info/licenses/LICENSE
pymssql_mcp-0.4.2.dist-info/RECORD
