Metadata-Version: 2.4
Name: pymssql-mcp
Version: 0.4.2
Summary: MCP server for Microsoft SQL Server databases
Project-URL: Homepage, https://github.com/bpamiri/pymssql-mcp
Project-URL: Documentation, https://github.com/bpamiri/pymssql-mcp#readme
Project-URL: Repository, https://github.com/bpamiri/pymssql-mcp
Project-URL: Issues, https://github.com/bpamiri/pymssql-mcp/issues
Author-email: Peter <peter@example.com>
License-Expression: Apache-2.0
License-File: LICENSE
Keywords: database,mcp,mssql,sql,sqlserver
Classifier: Development Status :: 3 - Alpha
Classifier: Intended Audience :: Developers
Classifier: License :: OSI Approved :: Apache Software License
Classifier: Programming Language :: Python :: 3
Classifier: Programming Language :: Python :: 3.10
Classifier: Programming Language :: Python :: 3.11
Classifier: Programming Language :: Python :: 3.12
Classifier: Topic :: Database
Requires-Python: >=3.10
Requires-Dist: httpx>=0.25.0
Requires-Dist: mcp>=1.24.0
Requires-Dist: pydantic-settings>=2.0.0
Requires-Dist: pymssql>=2.2.0
Requires-Dist: starlette>=0.27.0
Requires-Dist: uvicorn>=0.30.0
Provides-Extra: dev
Requires-Dist: mypy>=1.0.0; extra == 'dev'
Requires-Dist: pytest-asyncio>=0.21.0; extra == 'dev'
Requires-Dist: pytest-cov>=4.0.0; extra == 'dev'
Requires-Dist: pytest-mock>=3.0.0; extra == 'dev'
Requires-Dist: pytest>=7.0.0; extra == 'dev'
Requires-Dist: ruff>=0.1.0; extra == 'dev'
